LICENSE.md
MANIFEST.in
README.md
dynamic_extras_require.txt
dynamic_install_requires.txt
quicklib_incorporated.v2.5.zip
quicklib_setup_from_yml.py
ultima/__init__.py
ultima/__version__.py
ultima/_mapping.py
ultima/_recursive.py
ultima/_registry.py
ultima/_workerapi.py
ultima/args.py
ultima/backend.py
ultima/bfr.py
ultima/inline.py
ultima/typing.py
ultima/utils.py
ultima/workforce.py
ultima.egg-info/PKG-INFO
ultima.egg-info/SOURCES.txt
ultima.egg-info/dependency_links.txt
ultima.egg-info/requires.txt
ultima.egg-info/top_level.txt
ultima/tests/__init__.py
ultima/tests/conftest.py
ultima/tests/test_recursive.py
ultima/tests/test_ultima.py